wrapanapi/__init__.py
wrapanapi/const.py
wrapanapi/exceptions.py
wrapanapi/clients/__init__.py
wrapanapi/clients/rest_client.py
wrapanapi/clients/websocket_client.py
wrapanapi/entities/__init__.py
wrapanapi/entities/base.py
wrapanapi/entities/instance.py
wrapanapi/entities/network.py
wrapanapi/entities/physical_container.py
wrapanapi/entities/server.py
wrapanapi/entities/stack.py
wrapanapi/entities/template.py
wrapanapi/entities/vm.py
wrapanapi/entities/volume.py
wrapanapi/systems/__init__.py
wrapanapi/systems/base.py
wrapanapi/systems/ec2.py
wrapanapi/systems/google.py
wrapanapi/systems/hawkular.py
wrapanapi/systems/lenovo.py
wrapanapi/systems/msazure.py
wrapanapi/systems/nuage.py
wrapanapi/systems/openstack.py
wrapanapi/systems/openstack_infra.py
wrapanapi/systems/redfish.py
wrapanapi/systems/rhevm.py
wrapanapi/systems/scvmm.py
wrapanapi/systems/vcloud.py
wrapanapi/systems/virtualcenter.py
wrapanapi/systems/container/__init__.py
wrapanapi/systems/container/podman.py
wrapanapi/systems/container/rhopenshift.py
wrapanapi/utils/__init__.py
wrapanapi/utils/json_utils.py
wrapanapi/utils/logger_mixin.py
wrapanapi/utils/random.py
wrapanapi-3.7.2.dist-info/METADATA
wrapanapi-3.7.2.dist-info/WHEEL
wrapanapi-3.7.2.dist-info/licenses/LICENSE
wrapanapi-3.7.2.dist-info/RECORD
