Metadata-Version: 2.4
Name: wrapanapi
Version: 3.7.2
Project-URL: Source, https://github.com/RedHatQE/wrapanapi
Author: Peter Savage
Maintainer: Jitendra Yejare, Mike Shriver
License-File: LICENSE
Keywords: api,cloud,distutils,hatch,hyperscaler
Requires-Python: >=3.9
Requires-Dist: azure-storage-common>=1.0
Requires-Dist: azure==4.0.0
Requires-Dist: boto
Requires-Dist: boto3
Requires-Dist: botocore
Requires-Dist: cached-property
Requires-Dist: dateparser
Requires-Dist: fauxfactory
Requires-Dist: google-api-python-client
Requires-Dist: google-compute-engine
Requires-Dist: inflection
Requires-Dist: lxml
Requires-Dist: miq-version
Requires-Dist: oauth2client
Requires-Dist: openshift==0.3.4
Requires-Dist: openstacksdk
Requires-Dist: ovirt-engine-sdk-python~=4.3
Requires-Dist: packaging
Requires-Dist: podman>5.0.0
Requires-Dist: py3winrm==0.0.1
Requires-Dist: pyopenssl==24.2.1
Requires-Dist: python-cinderclient
Requires-Dist: python-glanceclient
Requires-Dist: python-heatclient
Requires-Dist: python-ironicclient
Requires-Dist: python-keystoneclient
Requires-Dist: python-neutronclient==10.0.0
Requires-Dist: python-novaclient==18.10.0
Requires-Dist: python-swiftclient
Requires-Dist: pyvcloud==23.0.4
Requires-Dist: pyvmomi>=6.5.0.2017.5.post1
Requires-Dist: redfish-client==0.1.0
Requires-Dist: requests
Requires-Dist: tzlocal
Requires-Dist: vspk==5.3.2
Requires-Dist: wait-for
Requires-Dist: websocket-client
Provides-Extra: dev
Requires-Dist: pre-commit; extra == 'dev'
Provides-Extra: test
Requires-Dist: coveralls; extra == 'test'
Requires-Dist: mock; extra == 'test'
Requires-Dist: pytest; extra == 'test'
Requires-Dist: pytest-cov; extra == 'test'
Requires-Dist: pytest-mock; extra == 'test'
Requires-Dist: pytest-variables; extra == 'test'
